{
  "borrow: first": "188894",
  "borrow: second action, same reserve": "168843",
  "liquidationCall (receiveShares): full": "294609",
  "liquidationCall (receiveShares): partial": "294327",
  "liquidationCall: full": "303894",
  "liquidationCall: partial": "303612",
  "permitReserve + repay (multicall)": "164002",
  "permitReserve + supply (multicall)": "146269",
  "permitReserve + supply + enable collateral (multicall)": "160321",
  "repay: full": "123339",
  "repay: partial": "128309",
  "setUserPositionManagerWithSig: disable": "44890",
  "setUserPositionManagerWithSig: enable": "68931",
  "supply + enable collateral (multicall)": "140501",
  "supply: 0 borrows, collateral disabled": "122370",
  "supply: 0 borrows, collateral enabled": "105341",
  "supply: second action, same reserve": "105270",
  "updateUserDynamicConfig: 1 collateral": "74175",
  "updateUserDynamicConfig: 2 collaterals": "89080",
  "updateUserRiskPremium: 1 borrow": "94408",
  "updateUserRiskPremium: 2 borrows": "103543",
  "usingAsCollateral: 0 borrows, enable": "59205",
  "usingAsCollateral: 1 borrow, disable": "104523",
  "usingAsCollateral: 1 borrow, enable": "42093",
  "usingAsCollateral: 2 borrows, disable": "125619",
  "usingAsCollateral: 2 borrows, enable": "42105",
  "withdraw: 0 borrows, full": "127284",
  "withdraw: 0 borrows, partial": "131970",
  "withdraw: 1 borrow, partial": "158352",
  "withdraw: 2 borrows, partial": "172458",
  "withdraw: non collateral": "105240"
}