{
  "borrow: first": "223108",
  "borrow: second action, same reserve": "203680",
  "liquidationCall: full": "311172",
  "liquidationCall: partial": "331634",
  "permitReserve + repay (multicall)": "263675",
  "permitReserve + supply (multicall)": "145171",
  "permitReserve + supply + enable collateral (multicall)": "179149",
  "repay: full": "164860",
  "repay: partial": "207176",
  "setUserPositionManagerWithSig: disable": "44882",
  "setUserPositionManagerWithSig: enable": "68905",
  "supply + enable collateral (multicall)": "157091",
  "supply: 0 borrows, collateral disabled": "120050",
  "supply: 0 borrows, collateral enabled": "123194",
  "supply: 1 borrow": "123186",
  "supply: second action, same reserve": "106094",
  "updateUserDynamicConfig: 1 collateral": "73802",
  "updateUserDynamicConfig: 2 collaterals": "88662",
  "updateUserRiskPremium: 1 borrow": "154441",
  "updateUserRiskPremium: 2 borrows": "222413",
  "usingAsCollateral: 0 borrows, enable": "58976",
  "usingAsCollateral: 1 borrow, disable": "164700",
  "usingAsCollateral: 1 borrow, enable": "32298",
  "usingAsCollateral: 2 borrows, disable": "245746",
  "usingAsCollateral: 2 borrows, enable": "41876",
  "withdraw: 0 borrows, full": "131544",
  "withdraw: 0 borrows, partial": "138129",
  "withdraw: 1 borrow, partial": "224652",
  "withdraw: 2 borrows, partial": "305687",
  "withdraw: non collateral": "132737"
}